[
    {
        "titulo": "Linkedin",
        "img": "https://img.icons8.com/color/344/linkedin-circled--v1.png",
        "href": "https://www.linkedin.com/in/pedrovanzan/"

    },
    {
        "titulo": "GitHub",
        "img": "https://img.icons8.com/color/344/github.png",
        "href": "https://github.com/Vzn01"

    },
    {
        "titulo": "Instagram",
        "img": "https://img.icons8.com/fluency/344/instagram-new.png",
        "href": "https://www.instagram.com/pedro.vanzan/"
    }
]